dxpars/__init__.py
dxpars/document.py
dxpars/base/__init__.py
dxpars/base/base_objects.py
dxpars/docx_objects/__init__.py
dxpars/docx_objects/body.py
dxpars/docx_objects/paragraph.py
dxpars/docx_objects/table.py
dxpars/format/__init__.py
dxpars/format/paragraph.py
dxpars/format/table.py
dxpars-1.0.0.dist-info/licenses/LICENSE
dxpars-1.0.0.dist-info/METADATA
dxpars-1.0.0.dist-info/WHEEL
dxpars-1.0.0.dist-info/top_level.txt
dxpars-1.0.0.dist-info/RECORD
