Metadata-Version: 2.4
Name: dxpars
Version: 1.0.0
Summary: python docx parser
Author-email: Stepan Martiugin <stepanmartiugin@gmail.com>
License: MIT License
Project-URL: Homepage, https://github.com/stmyst/dxpars
Project-URL: Bug Tracker, https://github.com/stmyst/dxpars/issues
Classifier: Programming Language :: Python :: 3
Classifier: License :: OSI Approved :: MIT License
Classifier: Operating System :: OS Independent
Requires-Python: >=3.9
License-File: LICENSE
Requires-Dist: lxml~=6.0.0
Dynamic: license-file
